<?xml version="1.0" encoding="utf-8" ?>
<dwsync>
<file name="newBank.cfm" server="C:/inetpub/wwwroot/TM001/" local="129698135410000000" remote="129698135410000000" Dst="-1" />
<file name="updateBank.cfm" server="C:/inetpub/wwwroot/TM001/" local="129711933257122083" remote="129711933250000000" Dst="-1" />
<file name="newBank.cfm" server="ftp.nathconcept.com/TM001/" local="129995885322047879" remote="129995671200000000" Dst="0" />
<file name="updateBank.cfm" server="ftp.nathconcept.com/TM001/" local="129995885285975039" remote="129995671200000000" Dst="0" />
<file name="FundTransfer.cfm" server="C:/inetpub/wwwroot/TM001/" local="129719366973994262" remote="129719366970000000" Dst="-1" />
<file name="FundTransfer.cfm" server="ftp.nathconcept.com/TM001/" local="129995862184699479" remote="129995646600000000" Dst="0" />
<file name="AccountStatus.cfm" server="C:/inetpub/wwwroot/TM001/" local="129712912850986270" remote="129712912850000000" Dst="-1" />
<file name="AccountStatus.cfm" server="ftp.nathconcept.com/TM001/" local="129995886658835672" remote="129995671200000000" Dst="0" />
<file name="updateFundTransfer.cfm" server="C:/inetpub/wwwroot/TM001/" local="129763836010000000" remote="129763836010000000" Dst="-1" />
<file name="updateFundTransfer.cfm" server="ftp.nathconcept.com/TM001/" local="129995885860037466" remote="129995671200000000" Dst="0" />
<file name="FundTransfer.cfm" server="199.85.212.10/TM001/" local="129995862184699479" remote="130051747200000000" Dst="0" />
<file name="AccountStatus.cfm" server="199.85.212.10/TM001/" local="129995886658835672" remote="130051747200000000" Dst="0" />
<file name="newBank.cfm" server="199.85.212.10/TM001/" local="130139216217481030" remote="130138928400000000" Dst="0" />
<file name="updateFundTransfer.cfm" server="199.85.212.10/TM001/" local="129995885860037466" remote="130051747200000000" Dst="0" />
<file name="updateBank.cfm" server="199.85.212.10/TM001/" local="130072902280147630" remote="130072578600000000" Dst="0" />
<file name="AccountStatus.cfm" server="199.85.212.10/filph/" local="129995886658835672" remote="130078007400000000" Dst="0" />
<file name="FundTransfer.cfm" server="199.85.212.10/filph/" local="130172315040944197" remote="130172028000000000" Dst="0" />
<file name="newBank.cfm" server="199.85.212.10/filph/" local="129995885322047879" remote="130078007400000000" Dst="0" />
<file name="updateBank.cfm" server="199.85.212.10/filph/" local="130072902280147630" remote="130078007400000000" Dst="0" />
<file name="updateFundTransfer.cfm" server="199.85.212.10/filph/" local="129995885860037466" remote="130078007400000000" Dst="0" />
<file name="AccountStatus.cfm" server="199.85.212.10/westins/" local="129995886658835672" remote="130137242400000000" Dst="0" />
<file name="FundTransfer.cfm" server="199.85.212.10/westins/" local="130126215521082114" remote="130137242400000000" Dst="0" />
<file name="newBank.cfm" server="199.85.212.10/westins/" local="130139218104801914" remote="130138929600000000" Dst="0" />
<file name="updateBank.cfm" server="199.85.212.10/westins/" local="130072902280147630" remote="130137242400000000" Dst="0" />
<file name="updateFundTransfer.cfm" server="199.85.212.10/westins/" local="129995885860037466" remote="130137243000000000" Dst="0" />
<file name="updateBank.cfm" server="ftp.nathconcept.com/tm001/" local="130072902280147630" remote="130072688400000000" Dst="0" />
<file name="AccountStatus.cfm" server="199.85.212.10/filKano/" local="129995886658835672" remote="130077829200000000" Dst="0" />
<file name="FundTransfer.cfm" server="199.85.212.10/filKano/" local="130172315040944197" remote="130172032200000000" Dst="0" />
<file name="updateBank.cfm" server="199.85.212.10/filKano/" local="130072902280147630" remote="130077829200000000" Dst="0" />
<file name="newBank.cfm" server="199.85.212.10/filKano/" local="129995885322047879" remote="130077829200000000" Dst="0" />
<file name="updateFundTransfer.cfm" server="199.85.212.10/filKano/" local="129995885860037466" remote="130077829200000000" Dst="0" />
<file name="FundTransfer.cfm" server="199.85.212.10/filIkeja/" local="130172315040944197" remote="130172029800000000" Dst="0" />
<file name="AccountStatus.cfm" server="199.85.212.10/filIkeja/" local="129995886658835672" remote="130078014600000000" Dst="0" />
<file name="newBank.cfm" server="199.85.212.10/filIkeja/" local="129995885322047879" remote="130078014600000000" Dst="0" />
<file name="updateFundTransfer.cfm" server="199.85.212.10/filIkeja/" local="129995885860037466" remote="130078014600000000" Dst="0" />
<file name="updateBank.cfm" server="199.85.212.10/filIkeja/" local="130072902280147630" remote="130078015200000000" Dst="0" />
<file name="FundTransfer.cfm" server="199.85.212.10/demo/" local="130126215521082114" remote="130159504800000000" Dst="2" />
<file name="AccountStatus.cfm" server="199.85.212.10/demo/" local="129995886658835672" remote="130159504800000000" Dst="2" />
<file name="newBank.cfm" server="199.85.212.10/demo/" local="130139223980594060" remote="130159504800000000" Dst="2" />
<file name="updateBank.cfm" server="199.85.212.10/demo/" local="130072902280147630" remote="130159504800000000" Dst="2" />
<file name="updateFundTransfer.cfm" server="199.85.212.10/demo/" local="129995885860037466" remote="130159504800000000" Dst="2" />
<file name="AccountStatus.cfm" server="199.85.212.10/filAccra/" local="129995886658835672" remote="130173694800000000" Dst="0" />
<file name="FundTransfer.cfm" server="199.85.212.10/filAccra/" local="130172315040944197" remote="130173694800000000" Dst="0" />
<file name="newBank.cfm" server="199.85.212.10/filAccra/" local="130139223980594060" remote="130173694800000000" Dst="0" />
<file name="updateBank.cfm" server="199.85.212.10/filAccra/" local="130072902280147630" remote="130173694800000000" Dst="0" />
<file name="updateFundTransfer.cfm" server="199.85.212.10/filAccra/" local="129995885860037466" remote="130173694800000000" Dst="0" />
<file name="AccountStatus.cfm" server="199.85.212.10/filKumasi/" local="129995886658835672" remote="130173705000000000" Dst="0" />
<file name="FundTransfer.cfm" server="199.85.212.10/filKumasi/" local="130172315040944197" remote="130173705000000000" Dst="0" />
<file name="newBank.cfm" server="199.85.212.10/filKumasi/" local="130139223980594060" remote="130173705000000000" Dst="0" />
<file name="updateFundTransfer.cfm" server="199.85.212.10/filKumasi/" local="129995885860037466" remote="130173705000000000" Dst="0" />
<file name="updateBank.cfm" server="199.85.212.10/filKumasi/" local="130072902280147630" remote="130173705000000000" Dst="0" />
<file name="AccountStatus.cfm" server="ftp.transactmanager.com/awardglobal/" local="129995886660000000" remote="130531927800000000" Dst="0" />
<file name="FundTransfer.cfm" server="ftp.transactmanager.com/awardglobal/" local="130580132654621050" remote="130582495800000000" Dst="0" />
<file name="newBank.cfm" server="ftp.transactmanager.com/awardglobal/" local="130597186797756788" remote="130596863400000000" Dst="0" />
<file name="updateBank.cfm" server="ftp.transactmanager.com/awardglobal/" local="130582769717451837" remote="130582495800000000" Dst="0" />
<file name="updateFundTransfer.cfm" server="ftp.transactmanager.com/awardglobal/" local="130559552546500715" remote="130559264400000000" Dst="0" />
<file name="fundTransferList.cfm" server="ftp.transactmanager.com/awardglobal/" local="130580191322451167" remote="130582495800000000" Dst="0" />
<file name="fundTransferList.cfm" server="ftp.transactmanager.com/filAccra/" local="130580191322451167" remote="130583751600000000" Dst="0" />
<file name="updateBank.cfm" server="ftp.transactmanager.com/filAccra/" local="130582769717451837" remote="130583751600000000" Dst="0" />
<file name="AccountStatus.cfm" server="ftp.transactmanager.com/demo/" local="131131115087103727" remote="131133511200000000" Dst="0" />
<file name="FundTransfer.cfm" server="ftp.transactmanager.com/demo/" local="131131115087534090" remote="131133511200000000" Dst="0" />
<file name="fundTransferList.cfm" server="ftp.transactmanager.com/demo/" local="131131115087764237" remote="131133511200000000" Dst="0" />
<file name="newBank.cfm" server="ftp.transactmanager.com/demo/" local="131131115088028263" remote="131133511200000000" Dst="0" />
<file name="updateBank.cfm" server="ftp.transactmanager.com/demo/" local="131131115088213458" remote="131133511200000000" Dst="0" />
<file name="updateFundTransfer.cfm" server="ftp.transactmanager.com/demo/" local="131131115088399196" remote="131133511200000000" Dst="0" />
<file name="AccountStatus.cfm" server="ftp.transactmanager.com/ikd/" local="130668947690940475" remote="130673259000000000" Dst="0" />
<file name="FundTransfer.cfm" server="ftp.transactmanager.com/ikd/" local="130673582329301260" remote="130673259000000000" Dst="0" />
<file name="fundTransferList.cfm" server="ftp.transactmanager.com/ikd/" local="130668950361740634" remote="130673259000000000" Dst="0" />
<file name="newBank.cfm" server="ftp.transactmanager.com/ikd/" local="130668951016234302" remote="130673259000000000" Dst="0" />
<file name="updateBank.cfm" server="ftp.transactmanager.com/ikd/" local="130668952216481913" remote="130673259000000000" Dst="0" />
<file name="updateFundTransfer.cfm" server="ftp.transactmanager.com/ikd/" local="130685515360000000" remote="130728550800000000" Dst="0" />
<file name="checkDup.js" server="ftp.transactmanager.com/demo/" local="131131115087293889" remote="131133511200000000" Dst="0" />
<file name="AccountStatus.cfm" server="ftp.transactmanager.com/BryanCole/" local="130675362020000000" remote="130804981800000000" Dst="0" />
<file name="checkDup.js" server="ftp.transactmanager.com/BryanCole/" local="130792735245688446" remote="130804981800000000" Dst="0" />
<file name="FundTransfer.cfm" server="ftp.transactmanager.com/BryanCole/" local="130792730367798964" remote="130804981800000000" Dst="0" />
<file name="fundTransferList.cfm" server="ftp.transactmanager.com/BryanCole/" local="130668950380000000" remote="130804981800000000" Dst="0" />
<file name="updateBank.cfm" server="ftp.transactmanager.com/BryanCole/" local="130679097000000000" remote="130804981800000000" Dst="0" />
<file name="newBank.cfm" server="ftp.transactmanager.com/BryanCole/" local="130676271780000000" remote="130804981800000000" Dst="0" />
<file name="updateFundTransfer.cfm" server="ftp.transactmanager.com/BryanCole/" local="130685515360000000" remote="130804981800000000" Dst="0" />
<file name="AccountStatus.cfm" server="ftp.transactmanager.com/charis/" local="130675362020000000" remote="130821748800000000" Dst="0" />
<file name="checkDup.js" server="ftp.transactmanager.com/charis/" local="130792735245688446" remote="130821748800000000" Dst="0" />
<file name="FundTransfer.cfm" server="ftp.transactmanager.com/charis/" local="130792730367798964" remote="130821748800000000" Dst="0" />
<file name="fundTransferList.cfm" server="ftp.transactmanager.com/charis/" local="130668950380000000" remote="130821748800000000" Dst="0" />
<file name="newBank.cfm" server="ftp.transactmanager.com/charis/" local="130676271780000000" remote="130821748800000000" Dst="0" />
<file name="updateBank.cfm" server="ftp.transactmanager.com/charis/" local="130679097000000000" remote="130821748800000000" Dst="0" />
<file name="updateFundTransfer.cfm" server="ftp.transactmanager.com/charis/" local="130685515360000000" remote="130821748800000000" Dst="0" />
<file name="AccountStatus.cfm" server="transactmanager.com/filph2/" local="130675362020000000" remote="130965081000000000" Dst="0" />
<file name="checkDup.js" server="transactmanager.com/filph2/" local="130836238328293962" remote="130965081000000000" Dst="0" />
<file name="FundTransfer.cfm" server="transactmanager.com/filph2/" local="130792730367798964" remote="130965081000000000" Dst="0" />
<file name="fundTransferList.cfm" server="transactmanager.com/filph2/" local="130668950380000000" remote="130965081000000000" Dst="0" />
<file name="newBank.cfm" server="transactmanager.com/filph2/" local="130676271780000000" remote="130965081000000000" Dst="0" />
<file name="updateBank.cfm" server="transactmanager.com/filph2/" local="130679097000000000" remote="130965081000000000" Dst="0" />
<file name="updateFundTransfer.cfm" server="transactmanager.com/filph2/" local="130685515360000000" remote="130965081000000000" Dst="0" />
<file name="AccountStatus.cfm" server="ftp.transactmanager.com/filph/" local="130675362020000000" remote="130965075000000000" Dst="0" />
<file name="checkDup.js" server="ftp.transactmanager.com/filph/" local="130836238328293962" remote="130965075000000000" Dst="0" />
<file name="FundTransfer.cfm" server="ftp.transactmanager.com/filph/" local="130792730367798964" remote="130965075000000000" Dst="0" />
<file name="fundTransferList.cfm" server="ftp.transactmanager.com/filph/" local="130668950380000000" remote="130965075000000000" Dst="0" />
<file name="newBank.cfm" server="ftp.transactmanager.com/filph/" local="130676271780000000" remote="130965075000000000" Dst="0" />
<file name="updateBank.cfm" server="ftp.transactmanager.com/filph/" local="130679097000000000" remote="130965075000000000" Dst="0" />
<file name="updateFundTransfer.cfm" server="ftp.transactmanager.com/filph/" local="130685515360000000" remote="130965075000000000" Dst="0" />
<file name="AccountStatus.cfm" server="transactmanager.com/filph16/" local="130675362020000000" remote="130970281200000000" Dst="0" />
<file name="FundTransfer.cfm" server="transactmanager.com/filph16/" local="130792730367798964" remote="130970281200000000" Dst="0" />
<file name="checkDup.js" server="transactmanager.com/filph16/" local="130836238328293962" remote="130970281200000000" Dst="0" />
<file name="fundTransferList.cfm" server="transactmanager.com/filph16/" local="130668950380000000" remote="130970281200000000" Dst="0" />
<file name="newBank.cfm" server="transactmanager.com/filph16/" local="130676271780000000" remote="130970281200000000" Dst="0" />
<file name="updateBank.cfm" server="transactmanager.com/filph16/" local="130679097000000000" remote="130970281200000000" Dst="0" />
<file name="updateFundTransfer.cfm" server="transactmanager.com/filph16/" local="130685515360000000" remote="130970281200000000" Dst="0" />
<file name="checkDup.js" server="ftp.transactmanager.com/demo.transactmanager.com/" local="131131115087293889" remote="131377467000000000" Dst="0" />
<file name="FundTransfer.cfm" server="ftp.transactmanager.com/demo.transactmanager.com/" local="131377755146024763" remote="131377467000000000" Dst="0" />
<file name="AccountStatus.cfm" server="ftp.transactmanager.com/demo.transactmanager.com/" local="131131115087103727" remote="131377477200000000" Dst="0" />
<file name="newBank.cfm" server="ftp.transactmanager.com/demo.transactmanager.com/" local="131377761451471526" remote="131377477200000000" Dst="0" />
<file name="updateBank.cfm" server="ftp.transactmanager.com/demo.transactmanager.com/" local="131396499268005126" remote="131396211000000000" Dst="0" />
<file name="fundTransferList.cfm" server="ftp.transactmanager.com/demo.transactmanager.com/" local="131131115087764237" remote="131377477200000000" Dst="0" />
<file name="updateFundTransfer.cfm" server="ftp.transactmanager.com/demo.transactmanager.com/" local="131381839949851123" remote="131381551800000000" Dst="0" />
<file name="AccountStatus.cfm" server="ftp.transactmanager.com/stonemark/" local="131131115087103727" remote="131400594000000000" Dst="0" />
<file name="FundTransfer.cfm" server="ftp.transactmanager.com/stonemark/" local="131377755146024763" remote="131400594000000000" Dst="0" />
<file name="fundTransferList.cfm" server="ftp.transactmanager.com/stonemark/" local="131131115087764237" remote="131400594000000000" Dst="0" />
<file name="checkDup.js" server="ftp.transactmanager.com/stonemark/" local="131131115087293889" remote="131400594000000000" Dst="0" />
<file name="updateFundTransfer.cfm" server="ftp.transactmanager.com/stonemark/" local="131381839949851123" remote="131400594000000000" Dst="0" />
<file name="newBank.cfm" server="ftp.transactmanager.com/stonemark/" local="131377761451471526" remote="131400594000000000" Dst="0" />
<file name="updateBank.cfm" server="ftp.transactmanager.com/stonemark/" local="131396499268005126" remote="131400594000000000" Dst="0" />
</dwsync>